donpapi/__init__.py
donpapi/collectors/__init__.py
donpapi/collectors/certificates.py
donpapi/collectors/chromium.py
donpapi/collectors/credman.py
donpapi/collectors/firefox.py
donpapi/collectors/mobaxterm.py
donpapi/collectors/mremoteng.py
donpapi/collectors/rdcman.py
donpapi/collectors/recent_files.py
donpapi/collectors/sccm.py
donpapi/collectors/vaults.py
donpapi/collectors/vnc.py
donpapi/collectors/wifi.py
donpapi/core.py
donpapi/entry.py
donpapi/lib/__init__.py
donpapi/lib/config.py
donpapi/lib/database.py
donpapi/lib/first_run.py
donpapi/lib/logger.py
donpapi/lib/paths.py
donpapi/lib/secretsdump.py
donpapi/lib/utils.py
donpapi/res/donpapi.conf
donpapi/res/gui/assets/index-d962605a.js
donpapi/res/gui/assets/index-e5561866.css
donpapi/res/gui/assets/logo_lse-3de0d1e2.png
donpapi/res/gui/favicon.ico
donpapi/res/gui/index.html
donpapi/server.py
donpapi-2.0.1.dist-info/LICENSE
donpapi-2.0.1.dist-info/METADATA
donpapi-2.0.1.dist-info/WHEEL
donpapi-2.0.1.dist-info/entry_points.txt
donpapi-2.0.1.dist-info/RECORD
