Metadata-Version: 2.1
Name: donpapi
Version: 2.0.1
Summary: Dumping revelant information on compromised targets without AV detection
Home-page: https://github.com/login-securite/DonPAPI
License: 'GNU (GPLv3)
Author: Login Securite
Author-email: contact@login-securite.com
Requires-Python: >=3.9,<4.0
Classifier: Environment :: Console
Classifier: License :: Other/Proprietary License
Classifier: Programming Language :: Python :: 3
Classifier: Programming Language :: Python :: 3.9
Classifier: Programming Language :: Python :: 3.10
Classifier: Programming Language :: Python :: 3.11
Classifier: Topic :: Security
Requires-Dist: dploot (>=2.7.3,<3.0.0)
Requires-Dist: exrex (>=0.11.0,<0.12.0)
Requires-Dist: flask (>=3.0.3,<4.0.0)
Requires-Dist: flask-basicauth (>=0.2.0,<0.3.0)
Requires-Dist: flask-cors (>=4.0.1,<5.0.0)
Requires-Dist: flask-rich (>=0.4.1,<0.5.0)
Requires-Dist: impacket (>=0.11.0,<0.12.0)
Requires-Dist: jinja2 (>=3.1.4,<4.0.0)
Requires-Dist: marshmallow-sqlalchemy (>=1.0.0,<2.0.0)
Requires-Dist: rich (>=13.7.0,<14.0.0)
Requires-Dist: sqlalchemy (>=2.0.25,<3.0.0)
Requires-Dist: termcolor (>=2.4.0,<3.0.0)
Project-URL: Repository, https://github.com/login-securite/DonPAPI
